{
  "numin": 549.979816,
  "numax": 6500.057219,
  "npnts": 98733,
  "sigma_max": 6.806176496935852e-19,
  "temperature": 323.15,
  "pressure": 760.0,
  "resolution": 0.112,
  "resolution_units": "cm-1",
  "broadener": "N2",
  "srcfile": "C3H4O2_323.1K-760.0Torr_550.0-6500.1_0.11_N2_540_62.txt",
  "srcdir": "cross_section_data/Methylglyoxal.zip",
  "srcformat": "2col",
  "__class__": "CrossSection",
  "source_alias": "Johnson et al. (2010)",
  "molecule_alias": "Methyl glyoxal",
  "experiment_alias": "EXPERIMENT"
}